nexafs/__init__.py
nexafs/core.py
nexafs-0.1.2.dist-info/METADATA
nexafs-0.1.2.dist-info/WHEEL
nexafs-0.1.2.dist-info/RECORD
